Robs_Toolbox2/GUITools.py
Robs_Toolbox2/__init__.py
Robs_Toolbox2/filehandler.py
Robs_Toolbox2/requesthelper.py
Robs_Toolbox2/toolbox.py
Robs_Toolbox2/xlsx.py
RobsToolbox2-1.0.10.dist-info/LICENSE
RobsToolbox2-1.0.10.dist-info/METADATA
RobsToolbox2-1.0.10.dist-info/WHEEL
RobsToolbox2-1.0.10.dist-info/top_level.txt
RobsToolbox2-1.0.10.dist-info/RECORD
