Metadata-Version: 2.1
Name: RobsToolbox2
Version: 1.0.10
Summary: General toolbox
Home-page: https://github.hy-vee.cloud/regli/Robs_Toolbox2
Author: Rob Egli
Author-email: regli@hy-vee.com
License: UNKNOWN
Project-URL: Bug Tracker, https://github.hy-vee.cloud/regli/Robs_Toolbox2/isssues
Platform: UNKNOWN
Classifier: Programming Language :: Python :: 3
Classifier: License :: OSI Approved :: MIT License
Classifier: Operating System :: OS Independent
Requires-Python: >=3.6
License-File: LICENSE
Requires-Dist: logzero
Requires-Dist: PyYAML
Requires-Dist: requests
